FileCache/FileCache.py
FileCache/__init__.py
FileCache_jingle1267-0.1.0.dist-info/LICENSE
FileCache_jingle1267-0.1.0.dist-info/METADATA
FileCache_jingle1267-0.1.0.dist-info/WHEEL
FileCache_jingle1267-0.1.0.dist-info/top_level.txt
FileCache_jingle1267-0.1.0.dist-info/RECORD
